AUTHORS
LICENSE
MANIFEST.in
README.md
setup.py
examples/__init__.py
examples/classify_insults.py
examples/iris.py
ramp/__init__.py
ramp/builders.py
ramp/configuration.py
ramp/context.py
ramp/metrics.py
ramp/models.py
ramp/reporters.py
ramp/selectors.py
ramp/shortcuts.py
ramp/store.py
ramp/utils.py
ramp.egg-info/PKG-INFO
ramp.egg-info/SOURCES.txt
ramp.egg-info/dependency_links.txt
ramp.egg-info/not-zip-safe
ramp.egg-info/top_level.txt
ramp/estimators/__init__.py
ramp/estimators/r.py
ramp/estimators/sk.py
ramp/features/__init__.py
ramp/features/base.py
ramp/features/combo.py
ramp/features/sparse.py
ramp/features/text.py
ramp/features/trained.py
ramp/tests/__init__.py
ramp/tests/test_configuration.py
ramp/tests/test_features.py
ramp/tests/test_store.py
ramp/tests/test_utils.py