Metadata-Version: 1.0
Name: ramp
Version: 0.1.4
Summary: Rapid machine learning prototyping
Home-page: http://github.com/kvh/ramp
Author: Ken Van Haren
Author-email: kvh@science.io
License: BSD
Keywords: machine learning data analysis statistics mining
Platform: UNKNOWN
Classifier: License :: OSI Approved :: BSD License
